{
  "usersPoints": {
    "356541379960242186": {
      "points": 1100,
      "name": "sweetdebilus",
      "wins": 0,
      "losses": 0,
      "isDebilus": false,
      "inventory": 3
    },
    "719726331457437756": {
      "points": 100,
      "name": "risa.alisa",
      "wins": 0,
      "losses": 0,
      "isDebilus": false,
      "inventory": 3
    },
    "185852644890378241": {
      "points": 100,
      "name": "Shima",
      "wins": 0,
      "losses": 0,
      "isDebilus": false,
      "inventory": 3
    }
  },
  "debilusCloset": 0,
  "lastUpdateTime": "2024-10-29T14:09:02.599Z"
}